redgtech_api/__init__.py
redgtech_api/api.py
redgtech_api/py.typed
redgtech_api-0.1.37.dist-info/licenses/LICENSE
redgtech_api-0.1.37.dist-info/METADATA
redgtech_api-0.1.37.dist-info/WHEEL
redgtech_api-0.1.37.dist-info/top_level.txt
redgtech_api-0.1.37.dist-info/RECORD
