Metadata-Version: 2.4
Name: redgtech-api
Version: 0.1.37
Summary: A Python package to interact with the Redgtech API
Home-page: https://github.com/redgtech-automacao/redgtech-python-api
Author: Jonh Sady
Author-email: jonh.system@gmail.com
License: MIT
Classifier: Programming Language :: Python :: 3
Classifier: License :: OSI Approved :: MIT License
Classifier: Operating System :: OS Independent
Requires-Python: >=3.10
License-File: LICENSE
Requires-Dist: aiohttp>=3.7.4
Dynamic: author
Dynamic: author-email
Dynamic: classifier
Dynamic: description
Dynamic: description-content-type
Dynamic: home-page
Dynamic: license
Dynamic: license-file
Dynamic: requires-dist
Dynamic: requires-python
Dynamic: summary
